napari_tapenade_processing/__init__.py
napari_tapenade_processing/_custom_widgets.py
napari_tapenade_processing/_macro_recorder.py
napari_tapenade_processing/_processing_graph.py
napari_tapenade_processing/_widget.py
napari_tapenade_processing/napari.yaml
napari_tapenade_processing/logo/__init__.py
napari_tapenade_processing/logo/tapenade3.png
napari_tapenade_processing-0.0.14.dist-info/licenses/LICENSE
napari_tapenade_processing-0.0.14.dist-info/METADATA
napari_tapenade_processing-0.0.14.dist-info/WHEEL
napari_tapenade_processing-0.0.14.dist-info/entry_points.txt
napari_tapenade_processing-0.0.14.dist-info/top_level.txt
napari_tapenade_processing-0.0.14.dist-info/RECORD
