Metadata-Version: 2.4
Name: napari-tapenade-processing
Version: 0.0.14
Summary: A visual pipeline to process images with Tapenade in Napari
Home-page: https://github.com/jules-vanaret/napari-tapenade-processing
Author: Jules Vanaret
Author-email: jules.vanaret@univ-amu.fr
License: MIT
Project-URL: Bug Tracker, https://github.com/jules-vanaret/napari-tapenade-processing/issues
Project-URL: Documentation, https://github.com/jules-vanaret/napari-tapenade-processing#README.md
Project-URL: Source Code, https://github.com/jules-vanaret/napari-tapenade-processing
Project-URL: User Support, https://github.com/jules-vanaret/napari-tapenade-processing/issues
Classifier: Development Status :: 2 - Pre-Alpha
Classifier: Framework :: napari
Classifier: Intended Audience :: Developers
Classifier: License :: OSI Approved :: MIT License
Classifier: Operating System :: OS Independent
Classifier: Programming Language :: Python
Classifier: Programming Language :: Python :: 3
Classifier: Programming Language :: Python :: 3 :: Only
Classifier: Programming Language :: Python :: 3.8
Classifier: Programming Language :: Python :: 3.9
Classifier: Programming Language :: Python :: 3.10
Classifier: Topic :: Scientific/Engineering :: Image Processing
Requires-Python: >=3.8
License-File: LICENSE
Requires-Dist: numpy
Requires-Dist: magicgui
Requires-Dist: qtpy
Requires-Dist: tifffile
Requires-Dist: natsort
Requires-Dist: tapenade>=0.0.18
Provides-Extra: testing
Requires-Dist: tox; extra == "testing"
Requires-Dist: pytest; extra == "testing"
Requires-Dist: pytest-cov; extra == "testing"
Requires-Dist: pytest-qt; extra == "testing"
Requires-Dist: napari; extra == "testing"
Requires-Dist: pyqt5; extra == "testing"
Dynamic: license-file
